{"trial_id": "0006", "hyperparameters": {"space": [{"class_name": "Float", "config": {"name": "dropout", "default": 0.1, "conditions": [], "min_value": 0.1, "max_value": 0.5, "step": 0.1, "sampling": "linear"}}, {"class_name": "Choice", "config": {"name": "lr", "default": 0.01, "conditions": [], "values": [0.01, 0.001, 0.0001], "ordered": true}}], "values": {"dropout": 0.5, "lr": 0.01, "tuner/epochs": 8, "tuner/initial_epoch": 3, "tuner/bracket": 1, "tuner/round": 1, "tuner/trial_id": "0001"}}, "metrics": {"metrics": {"loss": {"direction": "min", "observations": [{"value": [1.4771579504013062], "step": 2}]}, "accuracy": {"direction": "max", "observations": [{"value": [0.5952611565589905], "step": 2}]}, "val_loss": {"direction": "min", "observations": [{"value": [1.1916195154190063], "step": 2}]}, "val_accuracy": {"direction": "max", "observations": [{"value": [0.669956386089325], "step": 2}]}, "lr": {"direction": "min", "observations": [{"value": [0.009999999776482582], "step": 2}]}}}, "score": 0.669956386089325, "best_step": 2, "status": "COMPLETED", "message": null}